channel_surfer/__init__.py
channel_surfer/main.py
channel_surfer-0.1.4.dist-info/METADATA
channel_surfer-0.1.4.dist-info/WHEEL
channel_surfer-0.1.4.dist-info/entry_points.txt
channel_surfer-0.1.4.dist-info/top_level.txt
channel_surfer-0.1.4.dist-info/RECORD
